img_term/__init__.py
img_term/img_term.py
img_term/plasma.py
img_term-1.0.2.dist-info/METADATA
img_term-1.0.2.dist-info/WHEEL
img_term-1.0.2.dist-info/entry_points.txt
img_term-1.0.2.dist-info/top_level.txt
img_term-1.0.2.dist-info/RECORD
