Metadata-Version: 2.1
Name: img-term
Version: 1.0.2
Summary: A small script to render images to an ANSI terminal
Home-page: https://github.com/jonnoFTW/img_term
Author: Jonathan Mackenzie
License: UNKNOWN
Project-URL: Bug Reports, https://github.com/jonnoFTW/img_term/issues
Project-URL: Source, https://github.com/jonnoFTW/img_term/
Keywords: terminal ansi fun
Platform: UNKNOWN
Classifier: License :: OSI Approved :: MIT License
Classifier: Programming Language :: Python :: 3
Classifier: Programming Language :: Python :: 3.4
Classifier: Programming Language :: Python :: 3.5
Classifier: Programming Language :: Python :: 3.6
Classifier: Programming Language :: Python :: 3.7
Requires-Dist: numba
Requires-Dist: numpy
Requires-Dist: opencv-python
